pelican_comment_system/__init__.py
pelican_comment_system/avatars.py
pelican_comment_system/comment.py
pelican_comment_system/identicon/__init__.py
pelican_comment_system/identicon/identicon.py
pelican_comment_system-1.4.0.dist-info/DESCRIPTION.rst
pelican_comment_system-1.4.0.dist-info/METADATA
pelican_comment_system-1.4.0.dist-info/RECORD
pelican_comment_system-1.4.0.dist-info/WHEEL
pelican_comment_system-1.4.0.dist-info/metadata.json
pelican_comment_system-1.4.0.dist-info/top_level.txt
