Metadata-Version: 2.0
Name: pelican-comment-system
Version: 1.4.0
Summary: Allows you to add static comments to your articles on your Pelican blog.
Home-page: https://github.com/Scheirle/pelican_comment_system
Author: Bernhard Scheirle
Author-email: bernhard+python@scheirle.de
License: UNKNOWN
Platform: UNKNOWN
Classifier: Development Status :: 5 - Production/Stable
Classifier: Environment :: Console
Classifier: License :: OSI Approved :: GNU General Public License v3 or later (GPLv3+)
Classifier: Operating System :: OS Independent
Classifier: Programming Language :: Python
Classifier: Programming Language :: Python :: 2
Classifier: Programming Language :: Python :: 3
Classifier: Topic :: Software Development :: Libraries :: Python Modules
Requires-Dist: pelican (>=3.4)
Requires-Dist: pillow
